pymessege/__init__.py
pymessege/_version.py
pymessege/cli.py
pymessege/entities/__init__.py
pymessege/enums/__init__.py
pymessege/services/__init__.py
pymessege/services/client/__init__.py
pymessege/services/client/messenger/__init__.py
pymessege/settings/__init__.py
pymessege/web/__init__.py
pymessege-0.0.8.dist-info/LICENSE
pymessege-0.0.8.dist-info/METADATA
pymessege-0.0.8.dist-info/WHEEL
pymessege-0.0.8.dist-info/top_level.txt
pymessege-0.0.8.dist-info/RECORD
