Metadata-Version: 2.1
Name: pymessege
Version: 0.0.8
Summary: pymessege
Home-page: https://github.com/toqp/pymessege
Author: Stanislav Tyshko
Author-email: admin@toqp.ru
License: Apache 2.0
Keywords: pymessege
Platform: UNKNOWN
Classifier: Development Status :: 1 - Planning
Classifier: Intended Audience :: Developers
Classifier: License :: OSI Approved :: Apache Software License
Classifier: Programming Language :: Python :: 3
Classifier: Programming Language :: Python :: 3.4
Classifier: Programming Language :: Python :: 3.5
Classifier: Programming Language :: Python :: 3.6
Classifier: Programming Language :: Python :: 3.7
Classifier: Programming Language :: Python :: 3.8
Classifier: Programming Language :: Python :: 3.9
Classifier: Programming Language :: Python
Classifier: Topic :: Internet
Requires-Python: >=2.7.10, !=3.0.*, !=3.1.*, !=3.2.*, !=3.3.*, !=3.4.0, !=3.4.1, !=3.4.2, ==3.9.* , <4
License-File: LICENSE
Requires-Dist: bleach (==4.1.0)
Requires-Dist: certifi (==2021.10.8)
Requires-Dist: charset-normalizer (==2.0.7)
Requires-Dist: click (==8.0.3)
Requires-Dist: colorama (==0.4.4)
Requires-Dist: docutils (==0.18)
Requires-Dist: idna (==3.3)
Requires-Dist: importlib-metadata (==4.8.2)
Requires-Dist: keyring (==23.2.1)
Requires-Dist: packaging (==21.3)
Requires-Dist: pkginfo (==1.8.1)
Requires-Dist: Pygments (==2.10.0)
Requires-Dist: pyparsing (==3.0.6)
Requires-Dist: pywin32-ctypes (==0.2.0)
Requires-Dist: readme-renderer (==30.0)
Requires-Dist: requests (==2.26.0)
Requires-Dist: requests-toolbelt (==0.9.1)
Requires-Dist: rfc3986 (==1.5.0)
Requires-Dist: six (==1.16.0)
Requires-Dist: tqdm (==4.62.3)
Requires-Dist: twine (==3.6.0)
Requires-Dist: urllib3 (==1.26.7)
Requires-Dist: webencodings (==0.5.1)
Requires-Dist: wincertstore (==0.2)
Requires-Dist: zipp (==3.6.0)
